aiotmdb/__init__.py
aiotmdb/aiotmdb.py
aiotmdb/exceptions.py
aiotmdb/resources/base.py
aiotmdb/resources/discover.py
aiotmdb/resources/genres.py
aiotmdb/resources/movies.py
aiotmdb/resources/search.py
aiotmdb/resources/tv.py
aiotmdb-0.4.dist-info/WHEEL
aiotmdb-0.4.dist-info/METADATA
aiotmdb-0.4.dist-info/RECORD
